msbench/__init__.py
msbench/app.py
msbench/client.py
msbench/limit.py
msbench/limit_from_start.py
msbench/time_range.py
msbench/timeframe.py
msbench-1.0.8.dist-info/LICENSE
msbench-1.0.8.dist-info/METADATA
msbench-1.0.8.dist-info/WHEEL
msbench-1.0.8.dist-info/entry_points.txt
msbench-1.0.8.dist-info/top_level.txt
msbench-1.0.8.dist-info/RECORD
